dycall/__init__.py
dycall/__main__.py
dycall/_widgets.py
dycall/about.py
dycall/app.py
dycall/demangler.py
dycall/desktop-app.json
dycall/exports.py
dycall/function.py
dycall/output.py
dycall/picker.py
dycall/runner.py
dycall/status_bar.py
dycall/top_menu.py
dycall/types.py
dycall/util.py
dycall/img/__init__.py
dycall/img/clock.png
dycall/img/dycall.ico
dycall/img/dycall.png
dycall/img/github.png
dycall/img/info.png
dycall/img/list.png
dycall/img/sort.png
dycall/img/sort_name_asc.png
dycall/img/sort_name_desc.png
dycall/img/theme.png
dycall/img/translate.png
dycall/msgs/__init__.py
dycall/msgs/hi.msg
dycall/msgs/mr.msg
dycall-0.0.8.dist-info/LICENSE
dycall-0.0.8.dist-info/METADATA
dycall-0.0.8.dist-info/WHEEL
dycall-0.0.8.dist-info/entry_points.txt
dycall-0.0.8.dist-info/top_level.txt
dycall-0.0.8.dist-info/RECORD
