Metadata-Version: 2.1
Name: dycall
Version: 0.0.8
Summary: Run exported symbols from native libraries
Home-page: https://github.com/demberto/dycall
Author: demberto
Author-email: demberto@protonmail.com
License: MIT
Project-URL: Repository, https://github.com/demberto/dycall/
Project-URL: Changelog, https://github.com/demberto/dycall/blob/master/CHANGELOG.md
Project-URL: Tracker, https://github.com/demberto/dycall/issues
Keywords: loader
Platform: UNKNOWN
Classifier: Development Status :: 3 - Alpha
Classifier: Intended Audience :: Developers
Classifier: Intended Audience :: End Users/Desktop
Classifier: License :: OSI Approved :: MIT License
Classifier: Natural Language :: English
Classifier: Natural Language :: Hindi
Classifier: Natural Language :: Marathi
Classifier: Operating System :: MacOS
Classifier: Operating System :: Microsoft :: Windows
Classifier: Operating System :: POSIX
Classifier: Programming Language :: Python :: 3
Classifier: Programming Language :: Python :: 3 :: Only
Classifier: Programming Language :: Python :: 3.7
Classifier: Programming Language :: Python :: 3.8
Classifier: Programming Language :: Python :: 3.9
Classifier: Programming Language :: Python :: 3.10
Classifier: Programming Language :: Tcl
Classifier: Topic :: Software Development :: Testing
Classifier: Topic :: Utilities
Classifier: Typing :: Typed
Requires-Python: >=3.7
License-File: LICENSE
Requires-Dist: EasySettings (>=4.0.1)
Requires-Dist: appdirs (>=1.4.4)
Requires-Dist: darkdetect (>=0.5.1)
Requires-Dist: desktop-app (>=0.2.10)
Requires-Dist: lief (>=0.11.5)
Requires-Dist: requests (>=2.27.1)
Requires-Dist: tkinter-tooltip (>=1.3.0)
Requires-Dist: tksheet (>=1.7.1)
Requires-Dist: ttkbootstrap (>=1.7.1)
Requires-Dist: cxxfilt (>=0.3.0) ; platform_system != "Windows"
Requires-Dist: pywin32 (>=303) ; platform_system == "Windows"
Requires-Dist: importlib-metadata ; python_version < "3.8"
